_win32typing-stubs/METADATA.toml
_win32typing-stubs/__init__.pyi
_win32typing-stubs/py.typed
commctrl-stubs/METADATA.toml
commctrl-stubs/__init__.pyi
commctrl-stubs/py.typed
dde-stubs/METADATA.toml
dde-stubs/__init__.pyi
dde-stubs/py.typed
isapi-stubs/METADATA.toml
isapi-stubs/__init__.pyi
isapi-stubs/install.pyi
isapi-stubs/isapicon.pyi
isapi-stubs/py.typed
isapi-stubs/simple.pyi
isapi-stubs/threaded_extension.pyi
mmapfile-stubs/METADATA.toml
mmapfile-stubs/__init__.pyi
mmapfile-stubs/py.typed
mmsystem-stubs/METADATA.toml
mmsystem-stubs/__init__.pyi
mmsystem-stubs/py.typed
ntsecuritycon-stubs/METADATA.toml
ntsecuritycon-stubs/__init__.pyi
ntsecuritycon-stubs/py.typed
odbc-stubs/METADATA.toml
odbc-stubs/__init__.pyi
odbc-stubs/py.typed
perfmon-stubs/METADATA.toml
perfmon-stubs/__init__.pyi
perfmon-stubs/py.typed
pythoncom-stubs/METADATA.toml
pythoncom-stubs/__init__.pyi
pythoncom-stubs/py.typed
pythonwin-stubs/METADATA.toml
pythonwin-stubs/__init__.pyi
pythonwin-stubs/dde.pyi
pythonwin-stubs/py.typed
pythonwin-stubs/win32ui.pyi
pythonwin-stubs/win32uiole.pyi
pywintypes-stubs/METADATA.toml
pywintypes-stubs/__init__.pyi
pywintypes-stubs/py.typed
regutil-stubs/METADATA.toml
regutil-stubs/__init__.pyi
regutil-stubs/py.typed
servicemanager-stubs/METADATA.toml
servicemanager-stubs/__init__.pyi
servicemanager-stubs/py.typed
sspicon-stubs/METADATA.toml
sspicon-stubs/__init__.pyi
sspicon-stubs/py.typed
timer-stubs/METADATA.toml
timer-stubs/__init__.pyi
timer-stubs/py.typed
types_pywin32-311.0.0.20250915.dist-info/licenses/LICENSE
win2kras-stubs/METADATA.toml
win2kras-stubs/__init__.pyi
win2kras-stubs/py.typed
win32-stubs/METADATA.toml
win32-stubs/__init__.pyi
win32-stubs/mmapfile.pyi
win32-stubs/odbc.pyi
win32-stubs/perfmon.pyi
win32-stubs/py.typed
win32-stubs/servicemanager.pyi
win32-stubs/timer.pyi
win32-stubs/win32api.pyi
win32-stubs/win32clipboard.pyi
win32-stubs/win32console.pyi
win32-stubs/win32cred.pyi
win32-stubs/win32crypt.pyi
win32-stubs/win32event.pyi
win32-stubs/win32evtlog.pyi
win32-stubs/win32file.pyi
types_pywin32-311.0.0.20250915.dist-info/METADATA
types_pywin32-311.0.0.20250915.dist-info/WHEEL
types_pywin32-311.0.0.20250915.dist-info/top_level.txt
types_pywin32-311.0.0.20250915.dist-info/RECORD
